Simbiber/BibTool.py
Simbiber/SimBiberTool.py
Simbiber/__init__.py
Simbiber/keep_keys.cfg
Simbiber/main.py
Simbiber/parserConfig.json
Simbiber/config/AI.json
Simbiber/config/Arch.json
Simbiber/config/CV.json
Simbiber/config/DM.json
Simbiber/config/IR.json
Simbiber/config/ML.json
Simbiber/config/NLP.json
Simbiber/config/Security.json
Simbiber/config/Sys.json
Simbiber/data/bibtex.bib
Simbiber/out/bibtex.bib
simbiber-0.8.1.dist-info/LICENSE
simbiber-0.8.1.dist-info/METADATA
simbiber-0.8.1.dist-info/WHEEL
simbiber-0.8.1.dist-info/entry_points.txt
simbiber-0.8.1.dist-info/top_level.txt
simbiber-0.8.1.dist-info/RECORD
