Metadata-Version: 2.1
Name: simbiber
Version: 0.8.1
Summary: a tool to fix and simplify bib automatically.
Home-page: https://github.com/MLNLP-World/SimBiber
Author: Qiguang Chen
Author-email: charleschen2333@gmail.com
License: MIT
Classifier: Development Status :: 4 - Beta
Classifier: Environment :: Console
Classifier: Topic :: Text Editors :: Text Processing
Classifier: Topic :: Text Processing :: Filters
Classifier: Topic :: Text Processing :: Markup :: LaTeX
Classifier: Programming Language :: Python
Classifier: Programming Language :: Python :: 3
Classifier: Programming Language :: Python :: 3.6
Classifier: Programming Language :: Python :: 3.7
Classifier: Programming Language :: Python :: 3.8
Classifier: Programming Language :: Python :: Implementation :: CPython
License-File: LICENSE
Requires-Dist: argparse
Requires-Dist: bibtexparser (>=1.2.0)
Requires-Dist: tqdm
